flask_thumbnails_s3-0.1.5.dist-info/RECORD
flask_thumbnails_s3-0.1.5.dist-info/DESCRIPTION.rst
flask_thumbnails_s3-0.1.5.dist-info/top_level.txt
flask_thumbnails_s3-0.1.5.dist-info/METADATA
flask_thumbnails_s3-0.1.5.dist-info/WHEEL
flask_thumbnails_s3-0.1.5.dist-info/metadata.json
flask_thumbnails_s3/__init__.py
