Metadata-Version: 2.0
Name: flask-thumbnails-s3
Version: 0.1.5
Summary: An extension to create image thumbnails on Amazon S3 (or on local storage) with the Flask framework, based on flask-thumbnails.
Home-page: https://github.com/Jaza/flask-thumbnails-s3
Author: Jeremy Epstein
Author-email: jazepstein@gmail.com
License: MIT
Platform: any
Classifier: Development Status :: 2 - Pre-Alpha
Classifier: Environment :: Web Environment
Classifier: Intended Audience :: Developers
Classifier: Operating System :: OS Independent
Classifier: Programming Language :: Python
Classifier: Programming Language :: Python :: 2
Classifier: Programming Language :: Python :: 2.7
Classifier: Programming Language :: Python :: 3
Classifier: Programming Language :: Python :: 3.3
Requires-Dist: Flask
Requires-Dist: Pillow
Requires-Dist: boto
Requires-Dist: url-for-s3
